reso_systemes/Gauss Seidel.py
reso_systemes/Jacobi.py
reso_systemes/Localisation.py
reso_systemes/Relaxation.py
reso_systemes/__init__.py
reso_systemes/cholesky.py
reso_systemes/descente.py
reso_systemes/dichotomie.py
reso_systemes/gauss.py
reso_systemes/newton-raphson.py
reso_systemes/remontee.py
ResolutionSystemesLineaireEtNon-0.1.1.dist-info/METADATA
ResolutionSystemesLineaireEtNon-0.1.1.dist-info/WHEEL
ResolutionSystemesLineaireEtNon-0.1.1.dist-info/top_level.txt
ResolutionSystemesLineaireEtNon-0.1.1.dist-info/RECORD
