Metadata-Version: 2.1
Name: ResolutionSystemesLineaireEtNon
Version: 0.1.1
Summary: Description de mon package
Author: Leo leo
Author-email: hocomi3722@exeneli.com
Classifier: Programming Language :: Python :: 3
Classifier: License :: OSI Approved :: MIT License
Classifier: Operating System :: OS Independent
Requires-Dist: numpy
Requires-Dist: matplotlib
